{
   "TopParent":{
      "Type":"ControlInfo",
      "Name":"helper",
      "Template":{
         "Id":"http://microsoft.com/appmagic/screen",
         "Version":"1.0",
         "LastModifiedTimestamp":"0",
         "Name":"screen",
         "FirstParty":true,
         "IsPremiumPcfControl":false,
         "IsCustomGroupControlTemplate":false,
         "CustomGroupControlTemplateName":"",
         "IsComponentDefinition":false,
         "OverridableProperties":{
            
         }
      },
      "Index":8.0,
      "PublishOrderIndex":0,
      "VariantName":"phoneLayout_FluidGridWithHeaderPageLayout_ver3.0",
      "LayoutName":"",
      "MetaDataIDKey":"",
      "PersistMetaDataIDKey":false,
      "IsFromScreenLayout":false,
      "StyleName":"defaultScreenStyle",
      "Parent":"",
      "IsDataControl":false,
      "AllowAccessToGlobals":true,
      "IsGroupControl":false,
      "IsAutoGenerated":false,
      "Rules":[
         {
            "Property":"Width",
            "Category":"Design",
            "InvariantScript":"Max(App.Width, App.MinScreenWidth)",
            "RuleProviderType":"Unknown"
         },
         {
            "Property":"Height",
            "Category":"Design",
            "InvariantScript":"Max(App.Height, App.MinScreenHeight)",
            "RuleProviderType":"Unknown"
         },
         {
            "Property":"ImagePosition",
            "Category":"Design",
            "InvariantScript":"ImagePosition.Fit",
            "RuleProviderType":"Unknown"
         },
         {
            "Property":"Fill",
            "Category":"Design",
            "InvariantScript":"RGBA(255, 255, 255, 1)",
            "RuleProviderType":"Unknown"
         },
         {
            "Property":"LoadingSpinner",
            "Category":"Design",
            "InvariantScript":"LoadingSpinner.None",
            "RuleProviderType":"Unknown"
         },
         {
            "Property":"LoadingSpinnerColor",
            "Category":"Design",
            "InvariantScript":"RGBA(100, 118, 132, 1)",
            "RuleProviderType":"Unknown"
         },
         {
            "Property":"Size",
            "Category":"Design",
            "InvariantScript":"1 + CountRows(App.SizeBreakpoints) - CountIf(App.SizeBreakpoints, Value >= Self.Width)",
            "RuleProviderType":"Unknown"
         },
         {
            "Property":"Orientation",
            "Category":"Design",
            "InvariantScript":"If(Self.Width < Self.Height, Layout.Vertical, Layout.Horizontal)",
            "RuleProviderType":"Unknown"
         }
      ],
      "ControlPropertyState":[
         "Fill",
         "ImagePosition",
         "Height",
         "Width",
         "Size",
         "Orientation",
         "LoadingSpinner",
         "LoadingSpinnerColor"
      ],
      "IsLocked":false,
      "ControlUniqueId":"80",
      "Children":[
         {
            "Type":"ControlInfo",
            "Name":"RectQuickActionBar1",
            "HasDynamicProperties":false,
            "Template":{
               "Id":"http://microsoft.com/appmagic/shapes/rectangle",
               "Version":"2.2.0",
               "LastModifiedTimestamp":"0",
               "Name":"rectangle",
               "FirstParty":true,
               "IsPremiumPcfControl":false,
               "IsCustomGroupControlTemplate":false,
               "CustomGroupControlTemplateName":"",
               "IsComponentDefinition":false,
               "OverridableProperties":{
                  
               }
            },
            "Index":0.0,
            "PublishOrderIndex":555,
            "VariantName":"",
            "LayoutName":"",
            "MetaDataIDKey":"%TemplatePhoneRectQuickActionBar.ID%",
            "PersistMetaDataIDKey":false,
            "IsFromScreenLayout":true,
            "StyleName":"invertedBackgroundRectangleStyle",
            "Parent":"helper",
            "IsDataControl":false,
            "AllowAccessToGlobals":true,
            "IsGroupControl":false,
            "IsAutoGenerated":false,
            "Rules":[
               {
                  "Property":"ContentLanguage",
                  "Category":"Data",
                  "InvariantScript":"\"\"",
                  "RuleProviderType":"Unknown"
               },
               {
                  "Property":"Fill",
                  "Category":"Design",
                  "InvariantScript":"RGBA(100, 118, 132, 1)",
                  "RuleProviderType":"Unknown"
               },
               {
                  "Property":"DisabledFill",
                  "Category":"Design",
                  "InvariantScript":"Self.Fill",
                  "RuleProviderType":"Unknown"
               },
               {
                  "Property":"PressedFill",
                  "Category":"Design",
                  "InvariantScript":"Self.Fill",
                  "RuleProviderType":"Unknown"
               },
               {
                  "Property":"HoverFill",
                  "Category":"Design",
                  "InvariantScript":"Self.Fill",
                  "RuleProviderType":"Unknown"
               },
               {
                  "Property":"BorderColor",
                  "Category":"Design",
                  "InvariantScript":"RGBA(32, 54, 71, 1)",
                  "RuleProviderType":"Unknown"
               },
               {
                  "Property":"BorderStyle",
                  "Category":"Design",
                  "InvariantScript":"BorderStyle.Solid",
                  "RuleProviderType":"Unknown"
               },
               {
                  "Property":"FocusedBorderColor",
                  "Category":"Design",
                  "InvariantScript":"Self.BorderColor",
                  "RuleProviderType":"Unknown"
               },
               {
                  "Property":"DisplayMode",
                  "Category":"Design",
                  "InvariantScript":"DisplayMode.Edit",
                  "RuleProviderType":"Unknown"
               },
               {
                  "Property":"X",
                  "Category":"Design",
                  "InvariantScript":"0",
                  "RuleProviderType":"Unknown"
               },
               {
                  "Property":"Y",
                  "Category":"Design",
                  "InvariantScript":"0",
                  "RuleProviderType":"Unknown"
               },
               {
                  "Property":"Width",
                  "Category":"Design",
                  "InvariantScript":"Parent.Width",
                  "RuleProviderType":"Unknown"
               },
               {
                  "Property":"Height",
                  "Category":"Design",
                  "InvariantScript":"88",
                  "RuleProviderType":"Unknown"
               },
               {
                  "Property":"ZIndex",
                  "Category":"Design",
                  "InvariantScript":"1",
                  "RuleProviderType":"Unknown"
               }
            ],
            "ControlPropertyState":[
               "Fill",
               "DisabledFill",
               "PressedFill",
               "HoverFill",
               "BorderColor",
               "BorderStyle",
               "FocusedBorderColor",
               "DisplayMode",
               "X",
               "Y",
               "Width",
               "Height",
               "ZIndex",
               "ContentLanguage"
            ],
            "IsLocked":false,
            "ControlUniqueId":"81",
            "Children":[
               
            ]
         },
         {
            "Type":"ControlInfo",
            "Name":"LblAppName1",
            "HasDynamicProperties":false,
            "Template":{
               "Id":"http://microsoft.com/appmagic/label",
               "Version":"2.4.0",
               "LastModifiedTimestamp":"0",
               "Name":"label",
               "FirstParty":true,
               "IsPremiumPcfControl":false,
               "IsCustomGroupControlTemplate":false,
               "CustomGroupControlTemplateName":"",
               "IsComponentDefinition":false,
               "OverridableProperties":{
                  
               }
            },
            "Index":0.0,
            "PublishOrderIndex":556,
            "VariantName":"",
            "LayoutName":"",
            "MetaDataIDKey":"%TemplatePhoneLblAppName.ID%",
            "PersistMetaDataIDKey":false,
            "IsFromScreenLayout":true,
            "StyleName":"invertedBkgHeaderLabelStyle",
            "Parent":"helper",
            "IsDataControl":false,
            "AllowAccessToGlobals":true,
            "IsGroupControl":false,
            "IsAutoGenerated":false,
            "Rules":[
               {
                  "Property":"Live",
                  "Category":"Data",
                  "InvariantScript":"Live.Off",
                  "RuleProviderType":"Unknown"
               },
               {
                  "Property":"Text",
                  "Category":"Data",
                  "InvariantScript":"\"[Título]\"",
                  "RuleProviderType":"Unknown"
               },
               {
                  "Property":"Role",
                  "Category":"Data",
                  "InvariantScript":"TextRole.Default",
                  "RuleProviderType":"Unknown"
               },
               {
                  "Property":"ContentLanguage",
                  "Category":"Data",
                  "InvariantScript":"\"\"",
                  "RuleProviderType":"Unknown"
               },
               {
                  "Property":"Overflow",
                  "Category":"Design",
                  "InvariantScript":"Overflow.Hidden",
                  "RuleProviderType":"Unknown"
               },
               {
                  "Property":"Color",
                  "Category":"Design",
                  "InvariantScript":"RGBA(255, 255, 255, 1)",
                  "RuleProviderType":"Unknown"
               },
               {
                  "Property":"DisabledColor",
                  "Category":"Design",
                  "InvariantScript":"RGBA(166, 166, 166, 1)",
                  "RuleProviderType":"Unknown"
               },
               {
                  "Property":"PressedColor",
                  "Category":"Design",
                  "InvariantScript":"Self.Color",
                  "RuleProviderType":"Unknown"
               },
               {
                  "Property":"HoverColor",
                  "Category":"Design",
                  "InvariantScript":"Self.Color",
                  "RuleProviderType":"Unknown"
               },
               {
                  "Property":"BorderColor",
                  "Category":"Design",
                  "InvariantScript":"RGBA(0, 0, 0, 1)",
                  "RuleProviderType":"Unknown"
               },
               {
                  "Property":"DisabledBorderColor",
                  "Category":"Design",
                  "InvariantScript":"RGBA(56, 56, 56, 1)",
                  "RuleProviderType":"Unknown"
               },
               {
                  "Property":"PressedBorderColor",
                  "Category":"Design",
                  "InvariantScript":"Self.BorderColor",
                  "RuleProviderType":"Unknown"
               },
               {
                  "Property":"HoverBorderColor",
                  "Category":"Design",
                  "InvariantScript":"Self.BorderColor",
                  "RuleProviderType":"Unknown"
               },
               {
                  "Property":"BorderStyle",
                  "Category":"Design",
                  "InvariantScript":"BorderStyle.Solid",
                  "RuleProviderType":"Unknown"
               },
               {
                  "Property":"FocusedBorderColor",
                  "Category":"Design",
                  "InvariantScript":"Self.BorderColor",
                  "RuleProviderType":"Unknown"
               },
               {
                  "Property":"Fill",
                  "Category":"Design",
                  "InvariantScript":"RGBA(0, 0, 0, 0)",
                  "RuleProviderType":"Unknown"
               },
               {
                  "Property":"DisabledFill",
                  "Category":"Design",
                  "InvariantScript":"RGBA(0, 0, 0, 0)",
                  "RuleProviderType":"Unknown"
               },
               {
                  "Property":"PressedFill",
                  "Category":"Design",
                  "InvariantScript":"Self.Fill",
                  "RuleProviderType":"Unknown"
               },
               {
                  "Property":"HoverFill",
                  "Category":"Design",
                  "InvariantScript":"Self.Fill",
                  "RuleProviderType":"Unknown"
               },
               {
                  "Property":"Font",
                  "Category":"Design",
                  "InvariantScript":"Font.'Open Sans'",
                  "RuleProviderType":"Unknown"
               },
               {
                  "Property":"FontWeight",
                  "Category":"Design",
                  "InvariantScript":"FontWeight.Normal",
                  "RuleProviderType":"Unknown"
               },
               {
                  "Property":"Align",
                  "Category":"Design",
                  "InvariantScript":"Align.Center",
                  "RuleProviderType":"Unknown"
               },
               {
                  "Property":"VerticalAlign",
                  "Category":"Design",
                  "InvariantScript":"VerticalAlign.Middle",
                  "RuleProviderType":"Unknown"
               },
               {
                  "Property":"X",
                  "Category":"Design",
                  "InvariantScript":"0",
                  "RuleProviderType":"Unknown"
               },
               {
                  "Property":"Y",
                  "Category":"Design",
                  "InvariantScript":"0",
                  "RuleProviderType":"Unknown"
               },
               {
                  "Property":"Width",
                  "Category":"Design",
                  "InvariantScript":"Parent.Width",
                  "RuleProviderType":"Unknown"
               },
               {
                  "Property":"Height",
                  "Category":"Design",
                  "InvariantScript":"88",
                  "RuleProviderType":"Unknown"
               },
               {
                  "Property":"DisplayMode",
                  "Category":"Design",
                  "InvariantScript":"DisplayMode.Edit",
                  "RuleProviderType":"Unknown"
               },
               {
                  "Property":"ZIndex",
                  "Category":"Design",
                  "InvariantScript":"2",
                  "RuleProviderType":"Unknown"
               },
               {
                  "Property":"Size",
                  "Category":"Design",
                  "InvariantScript":"18",
                  "RuleProviderType":"Unknown"
               }
            ],
            "ControlPropertyState":[
               {
                  "InvariantPropertyName":"Text",
                  "AutoRuleBindingEnabled":false,
                  "AutoRuleBindingString":"",
                  "NameMapSourceSchema":"?",
                  "IsLockable":false,
                  "AFDDataSourceName":""
               },
               "Live",
               "Overflow",
               "Role",
               "Color",
               "DisabledColor",
               "PressedColor",
               "HoverColor",
               "BorderColor",
               "DisabledBorderColor",
               "PressedBorderColor",
               "HoverBorderColor",
               "BorderStyle",
               "FocusedBorderColor",
               "Fill",
               "DisabledFill",
               "PressedFill",
               "HoverFill",
               "Font",
               "FontWeight",
               "Align",
               "VerticalAlign",
               "X",
               "Y",
               "Width",
               "Height",
               "DisplayMode",
               "ZIndex",
               "Size",
               "ContentLanguage"
            ],
            "IsLocked":false,
            "ControlUniqueId":"82",
            "Children":[
               
            ]
         },
         {
            "Type":"ControlInfo",
            "Name":"Canvas1",
            "HasDynamicProperties":false,
            "Template":{
               "Id":"http://microsoft.com/appmagic/fluidGrid",
               "Version":"2.2.0",
               "LastModifiedTimestamp":"0",
               "Name":"fluidGrid",
               "FirstParty":true,
               "IsPremiumPcfControl":false,
               "IsCustomGroupControlTemplate":false,
               "CustomGroupControlTemplateName":"",
               "IsComponentDefinition":false,
               "OverridableProperties":{
                  
               }
            },
            "Index":0.0,
            "PublishOrderIndex":557,
            "VariantName":"fluidGridWithBlankCard",
            "LayoutName":"",
            "MetaDataIDKey":"",
            "PersistMetaDataIDKey":false,
            "IsFromScreenLayout":true,
            "StyleName":"",
            "Parent":"helper",
            "IsDataControl":false,
            "AllowAccessToGlobals":true,
            "IsGroupControl":false,
            "IsAutoGenerated":false,
            "Rules":[
               {
                  "Property":"Reset",
                  "Category":"Data",
                  "InvariantScript":"false",
                  "RuleProviderType":"Unknown"
               },
               {
                  "Property":"ContentLanguage",
                  "Category":"Data",
                  "InvariantScript":"\"\"",
                  "RuleProviderType":"Unknown"
               },
               {
                  "Property":"BorderColor",
                  "Category":"Design",
                  "InvariantScript":"RGBA(0, 0, 0, 1)",
                  "RuleProviderType":"Unknown"
               },
               {
                  "Property":"BorderStyle",
                  "Category":"Design",
                  "InvariantScript":"BorderStyle.Solid",
                  "RuleProviderType":"Unknown"
               },
               {
                  "Property":"Fill",
                  "Category":"Design",
                  "InvariantScript":"RGBA(0, 0, 0, 0)",
                  "RuleProviderType":"Unknown"
               },
               {
                  "Property":"X",
                  "Category":"Design",
                  "InvariantScript":"0",
                  "RuleProviderType":"Unknown"
               },
               {
                  "Property":"Y",
                  "Category":"Design",
                  "InvariantScript":"RectQuickActionBar1.Y + RectQuickActionBar1.Height",
                  "RuleProviderType":"Unknown"
               },
               {
                  "Property":"Height",
                  "Category":"Design",
                  "InvariantScript":"Parent.Height - Self.Y",
                  "RuleProviderType":"Unknown"
               },
               {
                  "Property":"Width",
                  "Category":"Design",
                  "InvariantScript":"Parent.Width",
                  "RuleProviderType":"Unknown"
               },
               {
                  "Property":"DisplayMode",
                  "Category":"Design",
                  "InvariantScript":"DisplayMode.Edit",
                  "RuleProviderType":"Unknown"
               },
               {
                  "Property":"ZIndex",
                  "Category":"Design",
                  "InvariantScript":"3",
                  "RuleProviderType":"Unknown"
               },
               {
                  "Property":"BorderThickness",
                  "Category":"Design",
                  "InvariantScript":"0",
                  "RuleProviderType":"Unknown"
               }
            ],
            "ControlPropertyState":[
               "BorderColor",
               "BorderStyle",
               "Fill",
               "X",
               "Y",
               "Width",
               "Height",
               "DisplayMode",
               "ZIndex",
               "BorderThickness",
               "Reset",
               "ContentLanguage"
            ],
            "IsLocked":false,
            "ControlUniqueId":"83",
            "Children":[
               {
                  "Type":"ControlInfo",
                  "Name":"DataCard1",
                  "HasDynamicProperties":false,
                  "Template":{
                     "Id":"http://microsoft.com/appmagic/card",
                     "Version":"1.0.2",
                     "LastModifiedTimestamp":"0",
                     "Name":"dataCard",
                     "FirstParty":true,
                     "IsPremiumPcfControl":false,
                     "IsCustomGroupControlTemplate":false,
                     "CustomGroupControlTemplateName":"",
                     "IsComponentDefinition":false,
                     "OverridableProperties":{
                        
                     }
                  },
                  "Index":0.0,
                  "PublishOrderIndex":558,
                  "VariantName":"",
                  "LayoutName":"",
                  "MetaDataIDKey":"",
                  "PersistMetaDataIDKey":false,
                  "IsFromScreenLayout":true,
                  "StyleName":"",
                  "Parent":"Canvas1",
                  "IsDataControl":false,
                  "AllowAccessToGlobals":true,
                  "IsGroupControl":false,
                  "IsAutoGenerated":false,
                  "Rules":[
                     {
                        "Property":"BorderColor",
                        "Category":"Design",
                        "InvariantScript":"RGBA(0, 0, 0, 1)",
                        "RuleProviderType":"Unknown"
                     },
                     {
                        "Property":"BorderStyle",
                        "Category":"Design",
                        "InvariantScript":"BorderStyle.Solid",
                        "RuleProviderType":"Unknown"
                     },
                     {
                        "Property":"Fill",
                        "Category":"Design",
                        "InvariantScript":"RGBA(0, 0, 0, 0)",
                        "RuleProviderType":"Unknown"
                     },
                     {
                        "Property":"X",
                        "Category":"Design",
                        "InvariantScript":"0",
                        "RuleProviderType":"Unknown"
                     },
                     {
                        "Property":"Y",
                        "Category":"Design",
                        "InvariantScript":"0",
                        "RuleProviderType":"Unknown"
                     },
                     {
                        "Property":"Width",
                        "Category":"Design",
                        "InvariantScript":"Parent.Width",
                        "RuleProviderType":"Unknown"
                     },
                     {
                        "Property":"Height",
                        "Category":"Design",
                        "InvariantScript":"Parent.Height - 100",
                        "RuleProviderType":"Unknown"
                     },
                     {
                        "Property":"DisplayMode",
                        "Category":"Design",
                        "InvariantScript":"DisplayMode.Edit",
                        "RuleProviderType":"Unknown"
                     },
                     {
                        "Property":"ZIndex",
                        "Category":"Design",
                        "InvariantScript":"1",
                        "RuleProviderType":"Unknown"
                     },
                     {
                        "Property":"BorderThickness",
                        "Category":"Design",
                        "InvariantScript":"0",
                        "RuleProviderType":"Unknown"
                     }
                  ],
                  "ControlPropertyState":[
                     "BorderColor",
                     "BorderStyle",
                     "Fill",
                     "X",
                     "Y",
                     "Width",
                     "Height",
                     "DisplayMode",
                     "ZIndex",
                     "BorderThickness"
                  ],
                  "IsLocked":false,
                  "ControlUniqueId":"84",
                  "Children":[
                     
                  ]
               }
            ]
         }
      ]
   }
}